<annotation>
	<folder>fruta</folder>
	<filename>v33.png</filename>
	<path>D:\00-SERVICIOS\00_IA\IA RECONOCIMIENTO DE FRUTAS\fruta\v33.png</path>
	<source>
		<database>Unknown</database>
	</source>
	<size>
		<width>766</width>
		<height>863</height>
		<depth>3</depth>
	</size>
	<segmented>0</segmented>
	<object>
		<name>maracuya</name>
		<pose>Unspecified</pose>
		<truncated>0</truncated>
		<difficult>0</difficult>
		<bndbox>
			<xmin>345</xmin>
			<ymin>528</ymin>
			<xmax>587</xmax>
			<ymax>773</ymax>
		</bndbox>
	</object>
	<object>
		<name>maracuya</name>
		<pose>Unspecified</pose>
		<truncated>0</truncated>
		<difficult>0</difficult>
		<bndbox>
			<xmin>99</xmin>
			<ymin>423</ymin>
			<xmax>382</xmax>
			<ymax>761</ymax>
		</bndbox>
	</object>
</annotation>
